ranpass.py
app/__init__.py
app/__main__.py
app/application.py
ranpass-0.0.4.dist-info/LICENSE
ranpass-0.0.4.dist-info/METADATA
ranpass-0.0.4.dist-info/WHEEL
ranpass-0.0.4.dist-info/entry_points.txt
ranpass-0.0.4.dist-info/top_level.txt
ranpass-0.0.4.dist-info/RECORD
