Metadata-Version: 2.1
Name: ranpass
Version: 0.0.4
Summary: random password generator
Home-page: https://github.com/kanish671/ranpass
Author: Anish Krishnaswamy
Author-email: kanish671@gmail.com
License: MIT
Platform: UNKNOWN
Classifier: Programming Language :: Python :: 3.8
Classifier: License :: OSI Approved :: MIT License
Classifier: Operating System :: OS Independent
Requires-Python: >=3.7
License-File: LICENSE
Requires-Dist: click (>=8.0.1)
Requires-Dist: pyperclip (>=1.8.2)
